grid_pixelator/__init__.py
grid_pixelator/commands.py
grid_pixelator/image_label.py
grid_pixelator/image_utils.py
grid_pixelator/main_window.py
grid_pixelator-0.1.1.dist-info/licenses/LICENSE
grid_pixelator-0.1.1.dist-info/METADATA
grid_pixelator-0.1.1.dist-info/WHEEL
grid_pixelator-0.1.1.dist-info/entry_points.txt
grid_pixelator-0.1.1.dist-info/top_level.txt
grid_pixelator-0.1.1.dist-info/RECORD
