Metadata-Version: 2.4
Name: grid-pixelator
Version: 0.1.1
Summary: A simple GUI tool to pixelate images by averaging colors within a user-defined grid.
Author-email: tsuyoshi <tsuyo_suke.2112@icloud.com>
License: MIT License
Keywords: image,pixelate,pixel art,grid,average color,gui,pyqt
Classifier: Development Status :: 4 - Beta
Classifier: Intended Audience :: End Users/Desktop
Classifier: License :: OSI Approved :: MIT License
Classifier: Operating System :: MacOS
Classifier: Operating System :: Microsoft :: Windows
Classifier: Operating System :: POSIX :: Linux
Classifier: Programming Language :: Python :: 3
Classifier: Programming Language :: Python :: 3.8
Classifier: Programming Language :: Python :: 3.9
Classifier: Programming Language :: Python :: 3.10
Classifier: Programming Language :: Python :: 3.11
Classifier: Programming Language :: Python :: 3.12
Classifier: Topic :: Multimedia :: Graphics :: Editors
Classifier: Topic :: Multimedia :: Graphics :: Graphics Conversion
Classifier: Environment :: X11 Applications :: Qt
Requires-Python: >=3.8
License-File: LICENSE
Requires-Dist: PyQt6>=6.4
Requires-Dist: Pillow>=9.0
Provides-Extra: numpy
Requires-Dist: numpy>=1.20; extra == "numpy"
Dynamic: license-file
